google/cloud/datacatalog/__init__.py
google/cloud/datacatalog/gapic_version.py
google/cloud/datacatalog/py.typed
google/cloud/datacatalog_v1/__init__.py
google/cloud/datacatalog_v1/gapic_metadata.json
google/cloud/datacatalog_v1/gapic_version.py
google/cloud/datacatalog_v1/py.typed
google/cloud/datacatalog_v1/services/__init__.py
google/cloud/datacatalog_v1/services/data_catalog/__init__.py
google/cloud/datacatalog_v1/services/data_catalog/async_client.py
google/cloud/datacatalog_v1/services/data_catalog/client.py
google/cloud/datacatalog_v1/services/data_catalog/pagers.py
google/cloud/datacatalog_v1/services/data_catalog/transports/__init__.py
google/cloud/datacatalog_v1/services/data_catalog/transports/base.py
google/cloud/datacatalog_v1/services/data_catalog/transports/grpc.py
google/cloud/datacatalog_v1/services/data_catalog/transports/grpc_asyncio.py
google/cloud/datacatalog_v1/services/policy_tag_manager/__init__.py
google/cloud/datacatalog_v1/services/policy_tag_manager/async_client.py
google/cloud/datacatalog_v1/services/policy_tag_manager/client.py
google/cloud/datacatalog_v1/services/policy_tag_manager/pagers.py
google/cloud/datacatalog_v1/services/policy_tag_manager/transports/__init__.py
google/cloud/datacatalog_v1/services/policy_tag_manager/transports/base.py
google/cloud/datacatalog_v1/services/policy_tag_manager/transports/grpc.py
google/cloud/datacatalog_v1/services/policy_tag_manager/transports/grpc_asyncio.py
google/cloud/datacatalog_v1/services/policy_tag_manager_serialization/__init__.py
google/cloud/datacatalog_v1/services/policy_tag_manager_serialization/async_client.py
google/cloud/datacatalog_v1/services/policy_tag_manager_serialization/client.py
google/cloud/datacatalog_v1/services/policy_tag_manager_serialization/transports/__init__.py
google/cloud/datacatalog_v1/services/policy_tag_manager_serialization/transports/base.py
google/cloud/datacatalog_v1/services/policy_tag_manager_serialization/transports/grpc.py
google_cloud_datacatalog-3.27.1.dist-info/LICENSE
google_cloud_datacatalog-3.27.1.dist-info/METADATA
google_cloud_datacatalog-3.27.1.dist-info/WHEEL
google_cloud_datacatalog-3.27.1.dist-info/top_level.txt
google_cloud_datacatalog-3.27.1.dist-info/RECORD
